personal_library_manager/__init__.py
personal_library_manager/cli.py
personal_library_manager/library.py
personal_library_manager-0.1.1.dist-info/METADATA
personal_library_manager-0.1.1.dist-info/WHEEL
personal_library_manager-0.1.1.dist-info/entry_points.txt
personal_library_manager-0.1.1.dist-info/top_level.txt
personal_library_manager-0.1.1.dist-info/RECORD
