Metadata-Version: 2.4
Name: personal-library-manager
Version: 0.1.1
Summary: A CLI app to manage your personal book collection
Home-page: https://github.com/muhammadwaheedairi/personal-library-manager.git
Author: Muhammad waheed
Author-email: wm0297567@gmail.com
Classifier: Programming Language :: Python :: 3
Classifier: Operating System :: OS Independent
Requires-Python: >=3.6
Dynamic: author
Dynamic: author-email
Dynamic: classifier
Dynamic: description
Dynamic: description-content-type
Dynamic: home-page
Dynamic: requires-python
Dynamic: summary
